.cproject
.gitattributes
.gitignore
.gitmodules
.project
.pydevproject
LICENSE.md
MANIFEST.in
README.md
aksetup_helper.py
configure.py
setup.cfg
setup.py
.settings/org.eclipse.core.resources.prefs
c++/.gitignore
c++/Jamroot
c++/pyseqan_pch.h
c++/boost-indexing-suite/indexing_suite/algorithms.hpp
c++/boost-indexing-suite/indexing_suite/container_proxy.hpp
c++/boost-indexing-suite/indexing_suite/container_suite.hpp
c++/boost-indexing-suite/indexing_suite/container_traits.hpp
c++/boost-indexing-suite/indexing_suite/deque.hpp
c++/boost-indexing-suite/indexing_suite/element_proxy.hpp
c++/boost-indexing-suite/indexing_suite/element_proxy_traits.hpp
c++/boost-indexing-suite/indexing_suite/int_slice_helper.hpp
c++/boost-indexing-suite/indexing_suite/iterator_range.hpp
c++/boost-indexing-suite/indexing_suite/iterator_traits.hpp
c++/boost-indexing-suite/indexing_suite/list.hpp
c++/boost-indexing-suite/indexing_suite/map.hpp
c++/boost-indexing-suite/indexing_suite/methods.hpp
c++/boost-indexing-suite/indexing_suite/multimap.hpp
c++/boost-indexing-suite/indexing_suite/pair.hpp
c++/boost-indexing-suite/indexing_suite/proxy_iterator.hpp
c++/boost-indexing-suite/indexing_suite/python_iterator.hpp
c++/boost-indexing-suite/indexing_suite/set.hpp
c++/boost-indexing-suite/indexing_suite/shared_proxy_impl.hpp
c++/boost-indexing-suite/indexing_suite/slice.hpp
c++/boost-indexing-suite/indexing_suite/slice_handler.hpp
c++/boost-indexing-suite/indexing_suite/suite_utils.hpp
c++/boost-indexing-suite/indexing_suite/value_traits.hpp
c++/boost-indexing-suite/indexing_suite/vector.hpp
c++/boost-indexing-suite/indexing_suite/visitor.hpp
c++/boost-indexing-suite/indexing_suite/workaround.hpp
c++/bpl-tests/test_registry.py
c++/include/seqan/python/container.h
c++/include/seqan/python/defs.h
c++/include/seqan/python/index.h
c++/include/seqan/python/iterator.h
c++/include/seqan/python/modified.h
c++/include/seqan/python/names.h
c++/include/seqan/python/pch.h
c++/include/seqan/python/segment.h
python/pyseqan.egg-info/PKG-INFO
python/pyseqan.egg-info/SOURCES.txt
python/pyseqan.egg-info/dependency_links.txt
python/pyseqan.egg-info/requires.txt
python/pyseqan.egg-info/top_level.txt
