Metadata-Version: 1.1
Name: pyseqan
Version: 1.1.8
Summary: pyseqan: A package to expose SeqAn suffix array functionality.
Home-page: http://sysbio.mrc-bsu.cam.ac.uk/johns/pyseqan/docs/build/html/index.html
Author: John Reid
Author-email: johnbaronreid@netscape.net
License: BSD
Platform: UNKNOWN
Classifier: Development Status :: 5 - Production/Stable
Classifier: Environment :: Console
Classifier: Intended Audience :: Developers
Classifier: Intended Audience :: Science/Research
Classifier: License :: OSI Approved :: BSD License
Classifier: Operating System :: MacOS :: MacOS X
Classifier: Operating System :: POSIX
Classifier: Operating System :: Microsoft :: Windows
Classifier: Programming Language :: Python
Classifier: Programming Language :: C++
Classifier: Topic :: Scientific/Engineering
Classifier: Topic :: Scientific/Engineering :: Mathematics
Classifier: Topic :: Scientific/Engineering :: Bio-Informatics
Classifier: Topic :: Utilities
